ibats_bitmex_trader/__init__.py
ibats_bitmex_trader/config.py
ibats_bitmex_trader/agent/__init__.py
ibats_bitmex_trader/agent/md_agent.py
ibats_bitmex_trader/agent/td_agent.py
ibats_bitmex_trader/backend/__init__.py
ibats_bitmex_trader/backend/check.py
IBATS_BitMex_Trader-0.2.4.dist-info/LICENSE
IBATS_BitMex_Trader-0.2.4.dist-info/METADATA
IBATS_BitMex_Trader-0.2.4.dist-info/WHEEL
IBATS_BitMex_Trader-0.2.4.dist-info/top_level.txt
IBATS_BitMex_Trader-0.2.4.dist-info/RECORD
