Metadata-Version: 2.1
Name: IBATS-BitMex-Trader
Version: 0.2.4
Summary: 作为IBATS架构的 Trader 端，用于连接BitMex进行相应的交易及账户信息获取等动作
Home-page: https://github.com/IBATS/IBATS_BitMexTrader
Author: MG
Author-email: mmmaaaggg@163.com
License: UNKNOWN
Platform: UNKNOWN
Classifier: Programming Language :: Python :: 3 :: Only
Classifier: Programming Language :: Python :: 3.6
Classifier: Programming Language :: Python :: 3.7
Classifier: Operating System :: Microsoft :: Windows
Classifier: Operating System :: Unix
Classifier: Operating System :: POSIX
Classifier: License :: OSI Approved :: MIT License
Classifier: Development Status :: 5 - Production/Stable
Classifier: Environment :: No Input/Output (Daemon)
Classifier: Intended Audience :: Developers
Classifier: Natural Language :: Chinese (Simplified)
Classifier: Topic :: Software Development
Requires-Python: >=3.6
Requires-Dist: websocket
Requires-Dist: msgpack (>=0.5.6)
Requires-Dist: bitmex
Requires-Dist: bitmex-ws
Requires-Dist: IBATS-BitMex-Feeder
Requires-Dist: mysqlclient (>=1.3.8)
Requires-Dist: numpy (==1.14.4)
Requires-Dist: pandas (==0.23.0)
Requires-Dist: SQLAlchemy (==1.2.8)
